{"cameraMode":{"drawMode":0,"name":"Shaded","section":"Shading Mode"},"sceneLighting":true,"audioPlay":false,"sceneViewState":{"showFog":true,"showMaterialUpdate":false,"showSkybox":true,"showFlares":true,"showImageEffects":true,"showParticleSystems":true,"showVisualEffectGraphs":true,"m_FxEnabled":true},"in2DMode":false,"pivot":{"x":15.7280912399292,"y":-4.733612537384033,"z":-6.264747619628906},"rotation":{"x":0.0013916303869336844,"y":0.9570016860961914,"z":-0.29007840156555178,"w":0.004594653379172087},"size":19.90631103515625,"orthographic":false}